datasette_redirect_forbidden/__init__.py
datasette_redirect_forbidden-0.1.dist-info/LICENSE
datasette_redirect_forbidden-0.1.dist-info/METADATA
datasette_redirect_forbidden-0.1.dist-info/WHEEL
datasette_redirect_forbidden-0.1.dist-info/entry_points.txt
datasette_redirect_forbidden-0.1.dist-info/top_level.txt
datasette_redirect_forbidden-0.1.dist-info/RECORD
