Metadata-Version: 2.1
Name: datasette-redirect-forbidden
Version: 0.1
Summary: Redirect forbidden requests to a login page
Home-page: https://github.com/simonw/datasette-redirect-forbidden
Author: Simon Willison
License: Apache License, Version 2.0
Project-URL: Issues, https://github.com/simonw/datasette-redirect-forbidden/issues
Project-URL: CI, https://github.com/simonw/datasette-redirect-forbidden/actions
Project-URL: Changelog, https://github.com/simonw/datasette-redirect-forbidden/releases
Platform: UNKNOWN
Classifier: Framework :: Datasette
Classifier: License :: OSI Approved :: Apache Software License
Requires-Python: >=3.6
License-File: LICENSE
Requires-Dist: datasette
Provides-Extra: test
Requires-Dist: pytest ; extra == 'test'
Requires-Dist: pytest-asyncio ; extra == 'test'
